plotting_tools/__init__.py
plotting_tools/example.py
plotting_tools/plotting.py
plotting_tools-0.0.1.dist-info/LICENSE
plotting_tools-0.0.1.dist-info/METADATA
plotting_tools-0.0.1.dist-info/WHEEL
plotting_tools-0.0.1.dist-info/top_level.txt
plotting_tools-0.0.1.dist-info/RECORD
